ltchiptool/__init__.py
ltchiptool/__main__.py
ltchiptool/boards/_base/beken-7231-tuya.json
ltchiptool/boards/_base/beken-7231.json
ltchiptool/boards/_base/beken-7231n.json
ltchiptool/boards/_base/beken-7231q.json
ltchiptool/boards/_base/beken-7231t.json
ltchiptool/boards/_base/beken-7252.json
ltchiptool/boards/_base/beken-72xx.json
ltchiptool/boards/_base/generic.json
ltchiptool/boards/_base/ic/bk7231-qfn32.json
ltchiptool/boards/_base/ic/bk7231-qfn40.json
ltchiptool/boards/_base/ic/bk7231q-qfn40.json
ltchiptool/boards/_base/ic/bk7252-qfn68.json
ltchiptool/boards/_base/ic/ln882hk.json
ltchiptool/boards/_base/ic/rtl8710bn.json
ltchiptool/boards/_base/ic/rtl8720cf.json
ltchiptool/boards/_base/lightning-ln882hki.json
ltchiptool/boards/_base/lightning-ln882x.json
ltchiptool/boards/_base/pcb/afw121t.json
ltchiptool/boards/_base/pcb/bw12.json
ltchiptool/boards/_base/pcb/bw15.json
ltchiptool/boards/_base/pcb/cb1s-test.json
ltchiptool/boards/_base/pcb/cb1s.json
ltchiptool/boards/_base/pcb/cb2l-test.json
ltchiptool/boards/_base/pcb/cb2l.json
ltchiptool/boards/_base/pcb/cb2s-test.json
ltchiptool/boards/_base/pcb/cb2s.json
ltchiptool/boards/_base/pcb/cb3l.json
ltchiptool/boards/_base/pcb/cb3s.json
ltchiptool/boards/_base/pcb/cb3se.json
ltchiptool/boards/_base/pcb/cblc5-test.json
ltchiptool/boards/_base/pcb/cblc5.json
ltchiptool/boards/_base/pcb/cbu-test.json
ltchiptool/boards/_base/pcb/cbu.json
ltchiptool/boards/_base/pcb/ln-02-test.json
ltchiptool/boards/_base/pcb/ln-02.json
ltchiptool/boards/_base/pcb/lsc-lma35.json
ltchiptool/boards/_base/pcb/t102.json
ltchiptool/boards/_base/pcb/t103.json
ltchiptool/boards/_base/pcb/t112.json
ltchiptool/boards/_base/pcb/wa2-test.json
ltchiptool/boards/_base/pcb/wa2.json
ltchiptool/boards/_base/pcb/wb1s.json
ltchiptool/boards/_base/pcb/wb2l-m1-test.json
ltchiptool/boards/_base/pcb/wb2l-test.json
ltchiptool/boards/_base/pcb/wb2l.json
ltchiptool/boards/_base/pcb/wb2s-test.json
ltchiptool/boards/_base/pcb/wb2s.json
ltchiptool-4.12.2.dist-info/METADATA
ltchiptool-4.12.2.dist-info/WHEEL
ltchiptool-4.12.2.dist-info/entry_points.txt
ltchiptool-4.12.2.dist-info/licenses/LICENSE
ltchiptool-4.12.2.dist-info/RECORD
