Metadata-Version: 2.4
Name: ltchiptool
Version: 4.12.2
Summary: Universal flashing and binary manipulation tool for IoT chips
License: MIT
License-File: LICENSE
Author: Kuba Szczodrzyński
Author-email: kuba@szczodrzynski.pl
Requires-Python: >=3.7,<4.0
Classifier: License :: OSI Approved :: MIT License
Classifier: Programming Language :: Python :: 3
Classifier: Programming Language :: Python :: 3.7
Classifier: Programming Language :: Python :: 3.8
Classifier: Programming Language :: Python :: 3.9
Classifier: Programming Language :: Python :: 3.10
Classifier: Programming Language :: Python :: 3.11
Classifier: Programming Language :: Python :: 3.12
Classifier: Programming Language :: Python :: 3.13
Classifier: Programming Language :: Python :: 3.14
Provides-Extra: gui
Requires-Dist: bitstruct (>=8.1.1,<9.0.0)
Requires-Dist: bk7231tools (>=2.0.0,<3.0.0)
Requires-Dist: click (>=8.1.3,<9.0.0)
Requires-Dist: colorama (>=0.4.5,<0.5.0)
Requires-Dist: hexdump (>=3.3,<4.0)
Requires-Dist: importlib-metadata
Requires-Dist: prettytable (>=3.3.0,<4.0.0)
Requires-Dist: py-datastruct (>=1.0.0,<2.0.0)
Requires-Dist: pyaes (>=1.6.1,<2.0.0) ; platform_machine in "armv6l,armv7l,armv8l,armv8b,aarch64"
Requires-Dist: pycryptodome (>=3.9.9,<4.0.0) ; platform_machine not in "armv6l,armv7l,armv8l,armv8b,aarch64"
Requires-Dist: pylnk3 (>=0.4.2,<0.5.0) ; (sys_platform == "win32") and (extra == "gui")
Requires-Dist: pyuac (>=0.0.3,<0.0.4) ; (sys_platform == "win32") and (extra == "gui")
Requires-Dist: pywin32 ; (sys_platform == "win32") and (extra == "gui")
Requires-Dist: requests (>=2.31.0,<3.0.0)
Requires-Dist: semantic-version (>=2.10.0,<3.0.0)
Requires-Dist: wxPython (>=4.2.0,<5.0.0) ; extra == "gui"
Requires-Dist: xmodem (>=0.4.6,<0.5.0)
Requires-Dist: ymodem (>=1.5.1,<2.0.0)
Requires-Dist: zeroconf (<=0.128.4) ; extra == "gui"
